mongonator/__init__.py
mongonator/paginator.py
mongonator/pointermixin.py
mongonator/query.py
tests/__init__.py
tests/test_paginator.py
tests/test_pointermixin.py
tests/test_query.py
PyMongonnator-1.0.4.dist-info/LICENSE
PyMongonnator-1.0.4.dist-info/METADATA
PyMongonnator-1.0.4.dist-info/WHEEL
PyMongonnator-1.0.4.dist-info/top_level.txt
PyMongonnator-1.0.4.dist-info/RECORD
