Metadata-Version: 2.1
Name: PyMongonnator
Version: 1.0.4
Summary: Simple pymongo paginator using bucket pattern
Home-page: https://github.com/nitxiodev/py-mongonnator
Author: nitxiodev
Author-email: smnitxio@gmail.com
Classifier: Programming Language :: Python :: 3
Classifier: Programming Language :: Python :: 3.5
Classifier: Programming Language :: Python :: 3.6
Classifier: Programming Language :: Python :: 3.7
Classifier: Programming Language :: Python :: 3.8
Classifier: Programming Language :: Python :: 3.9
Classifier: Programming Language :: Python :: 3.10
Classifier: Programming Language :: Python :: 3.11
Classifier: License :: OSI Approved :: Apache Software License
Classifier: Operating System :: POSIX :: Linux
License-File: LICENSE
